README.md
setup.py
hypertuner/__init__.py
hypertuner/args.py
hypertuner/logger.py
hypertuner/saver.py
hypertuner.egg-info/PKG-INFO
hypertuner.egg-info/SOURCES.txt
hypertuner.egg-info/dependency_links.txt
hypertuner.egg-info/top_level.txt