Metadata-Version: 2.1
Name: hypertuner
Version: 1.0.4
Summary: A library for passing arguments and graphing with HyperTuner
Home-page: https://github.com/hypertuner/hypertuner-pythonlib
Author: Klemen Kotar, Dian Niu
Author-email: klemen@cs.washington.edu, dian.niu.11@gmail.com
License: UNKNOWN
Platform: UNKNOWN
Classifier: Programming Language :: Python :: 3
Classifier: License :: OSI Approved :: MIT License
Classifier: Operating System :: OS Independent
